{
  "$schema": "https://developer.microsoft.com/json-schemas/spfx/client-side-web-part-manifest.schema.json",
  "id": "87704b28-d9e7-495e-9b95-6fa4ffaeb0d2",
  "alias": "SpfxMailSendWpWebPart",
  "componentType": "WebPart",
  "version": "*",
  "manifestVersion": 2,
  "requiresCustomScript": false,
  "supportedHosts": [
    "SharePointWebPart",
    "TeamsPersonalApp",
    "TeamsTab",
    "SharePointFullPage"
  ],
  "supportsThemeVariants": true,
  "preconfiguredEntries": [
    {
      "groupId": "5c03119e-3074-46fd-976b-c60198311f70",
      "group": {
        "default": "Other"
      },
      "title": {
        "default": "spfx-mail-send-wp"
      },
      "description": {
        "default": "spfx-mail-send-wp description"
      },
      "officeFabricIconFontName": "Page",
      "properties": {
        "description": "spfx-mail-send-wp"
      }
    }
  ]
}